{
    "word": "door",
    "date": "20250711",
    "adapter": "merriam-webster",
    "data": [
        {
            "id": "door",
            "partOfSpeech": "noun",
            "text": "a usually swinging or sliding barrier by which an entry is closed and opened; also: a similar part of a piece of furniture",
            "attributionText": "from Merriam-Webster's Collegiate Dictionary",
            "sourceDictionary": "collegiate",
            "sourceUrl": "https://www.merriam-webster.com/dictionary/door",
            "examples": [
                "opens new doors",
                "door to success",
                "Doors are at 8, and music starts with Garrett Owen's set at 9pm."
            ]
        },
        {
            "id": "door",
            "partOfSpeech": "noun",
            "text": "doorway",
            "attributionText": "from Merriam-Webster's Collegiate Dictionary",
            "sourceDictionary": "collegiate",
            "sourceUrl": "https://www.merriam-webster.com/dictionary/door",
            "examples": [
                "opens new doors",
                "door to success",
                "Doors are at 8, and music starts with Garrett Owen's set at 9pm."
            ]
        },
        {
            "id": "door",
            "partOfSpeech": "noun",
            "text": "a means of access or participation: opportunity",
            "attributionText": "from Merriam-Webster's Collegiate Dictionary",
            "sourceDictionary": "collegiate",
            "sourceUrl": "https://www.merriam-webster.com/dictionary/door",
            "examples": [
                "opens new doors",
                "door to success",
                "Doors are at 8, and music starts with Garrett Owen's set at 9pm."
            ]
        },
        {
            "id": "door prize",
            "partOfSpeech": "noun",
            "text": "a prize awarded to the holder of a winning ticket passed out at the entrance to an entertainment or function",
            "attributionText": "from Merriam-Webster's Collegiate Dictionary",
            "sourceDictionary": "collegiate",
            "sourceUrl": "https://www.merriam-webster.com/dictionary/door"
        },
        {
            "id": "door-to-door",
            "partOfSpeech": "adjective",
            "text": "going or made by going to each house in a neighborhood",
            "attributionText": "from Merriam-Webster's Collegiate Dictionary",
            "sourceDictionary": "collegiate",
            "sourceUrl": "https://www.merriam-webster.com/dictionary/door",
            "examples": [
                "door-to-door salespeople",
                "a door-to-door canvass"
            ]
        },
        {
            "id": "Door Peninsula:g",
            "text": "peninsula in eastern Wisconsin between Green Bay and Lake Michigan",
            "attributionText": "from Merriam-Webster's Collegiate Dictionary",
            "sourceDictionary": "collegiate",
            "sourceUrl": "https://www.merriam-webster.com/dictionary/door"
        },
        {
            "id": "at death's door",
            "text": "close to death: critically ill",
            "attributionText": "from Merriam-Webster's Collegiate Dictionary",
            "sourceDictionary": "collegiate",
            "sourceUrl": "https://www.merriam-webster.com/dictionary/door"
        },
        {
            "id": "at one's door",
            "text": "as a charge against one as being responsible",
            "attributionText": "from Merriam-Webster's Collegiate Dictionary",
            "sourceDictionary": "collegiate",
            "sourceUrl": "https://www.merriam-webster.com/dictionary/door",
            "examples": [
                "laid the blame at our door"
            ]
        },
        {
            "id": "closed-door",
            "partOfSpeech": "adjective",
            "text": "barring public and press",
            "attributionText": "from Merriam-Webster's Collegiate Dictionary",
            "sourceDictionary": "collegiate",
            "sourceUrl": "https://www.merriam-webster.com/dictionary/door",
            "examples": [
                "a closed-door session of the investigating committee"
            ]
        },
        {
            "id": "close the door",
            "text": "to be uncompromisingly obstructive",
            "attributionText": "from Merriam-Webster's Collegiate Dictionary",
            "sourceDictionary": "collegiate",
            "sourceUrl": "https://www.merriam-webster.com/dictionary/door",
            "examples": [
                "closed the door to further negotiation"
            ]
        },
        {
            "id": "double door",
            "partOfSpeech": "noun",
            "text": "an opening with two vertical doors that meet in the middle of the opening when closed",
            "attributionText": "from Merriam-Webster's Collegiate Dictionary",
            "sourceDictionary": "collegiate",
            "sourceUrl": "https://www.merriam-webster.com/dictionary/door"
        }
    ]
}