{
    "word": "day",
    "date": "20250117",
    "adapter": "wordnik",
    "data": [
        {
            "id": "D5043200-1",
            "partOfSpeech": "noun",
            "attributionText": "from The American Heritage® Dictionary of the English Language, 5th Edition.",
            "sourceDictionary": "ahd-5",
            "text": "The period of light between dawn and nightfall; the interval from sunrise to sunset.",
            "sequence": "1",
            "score": 0,
            "word": "day",
            "attributionUrl": "https://ahdictionary.com/",
            "wordnikUrl": "https://www.wordnik.com/words/day",
            "citations": [],
            "exampleUses": [],
            "labels": [],
            "notes": [],
            "relatedWords": [],
            "textProns": []
        },
        {
            "id": "D5043200-2",
            "partOfSpeech": "noun",
            "attributionText": "from The American Heritage® Dictionary of the English Language, 5th Edition.",
            "sourceDictionary": "ahd-5",
            "sequence": "2",
            "score": 0,
            "word": "day",
            "attributionUrl": "https://ahdictionary.com/",
            "wordnikUrl": "https://www.wordnik.com/words/day",
            "citations": [],
            "exampleUses": [],
            "labels": [],
            "notes": [],
            "relatedWords": [],
            "textProns": []
        },
        {
            "id": "D5043200-3",
            "partOfSpeech": "noun",
            "attributionText": "from The American Heritage® Dictionary of the English Language, 5th Edition.",
            "sourceDictionary": "ahd-5",
            "text": "The 24-hour period during which the earth completes one rotation on its axis, traditionally measured from midnight to midnight.",
            "sequence": "3",
            "score": 0,
            "word": "day",
            "attributionUrl": "https://ahdictionary.com/",
            "wordnikUrl": "https://www.wordnik.com/words/day",
            "citations": [],
            "exampleUses": [],
            "labels": [],
            "notes": [],
            "relatedWords": [],
            "textProns": []
        },
        {
            "id": "D5043200-4",
            "partOfSpeech": "noun",
            "attributionText": "from The American Heritage® Dictionary of the English Language, 5th Edition.",
            "sourceDictionary": "ahd-5",
            "text": "The period during which a celestial body makes a similar rotation.",
            "sequence": "4",
            "score": 0,
            "word": "day",
            "attributionUrl": "https://ahdictionary.com/",
            "wordnikUrl": "https://www.wordnik.com/words/day",
            "citations": [],
            "exampleUses": [],
            "labels": [],
            "notes": [],
            "relatedWords": [],
            "textProns": []
        },
        {
            "id": "D5043200-5",
            "partOfSpeech": "noun",
            "attributionText": "from The American Heritage® Dictionary of the English Language, 5th Edition.",
            "sourceDictionary": "ahd-5",
            "text": "One of the numbered 24-hour periods into which a week, month, or year is divided.",
            "sequence": "5",
            "score": 0,
            "word": "day",
            "attributionUrl": "https://ahdictionary.com/",
            "wordnikUrl": "https://www.wordnik.com/words/day",
            "citations": [],
            "exampleUses": [],
            "labels": [],
            "notes": [],
            "relatedWords": [],
            "textProns": []
        },
        {
            "id": "D5043200-6",
            "partOfSpeech": "noun",
            "attributionText": "from The American Heritage® Dictionary of the English Language, 5th Edition.",
            "sourceDictionary": "ahd-5",
            "text": "The portion of a 24-hour period that is devoted to work, school, or business.",
            "sequence": "6",
            "score": 0,
            "word": "day",
            "exampleUses": [
                {
                    "text": "an eight-hour day; a sale that lasted for three days."
                }
            ],
            "attributionUrl": "https://ahdictionary.com/",
            "wordnikUrl": "https://www.wordnik.com/words/day",
            "citations": [],
            "labels": [],
            "notes": [],
            "relatedWords": [],
            "textProns": []
        },
        {
            "id": "D5043200-7",
            "partOfSpeech": "noun",
            "attributionText": "from The American Heritage® Dictionary of the English Language, 5th Edition.",
            "sourceDictionary": "ahd-5",
            "text": "A 24-hour period or a portion of it that is reserved for a certain activity.",
            "sequence": "7",
            "score": 0,
            "word": "day",
            "exampleUses": [
                {
                    "text": "a day of rest."
                }
            ],
            "attributionUrl": "https://ahdictionary.com/",
            "wordnikUrl": "https://www.wordnik.com/words/day",
            "citations": [],
            "labels": [],
            "notes": [],
            "relatedWords": [],
            "textProns": []
        },
        {
            "id": "D5043200-8",
            "partOfSpeech": "noun",
            "attributionText": "from The American Heritage® Dictionary of the English Language, 5th Edition.",
            "sourceDictionary": "ahd-5",
            "sequence": "8",
            "score": 0,
            "word": "day",
            "attributionUrl": "https://ahdictionary.com/",
            "wordnikUrl": "https://www.wordnik.com/words/day",
            "citations": [],
            "exampleUses": [],
            "labels": [],
            "notes": [],
            "relatedWords": [],
            "textProns": []
        },
        {
            "id": "D5043200-9",
            "partOfSpeech": "noun",
            "attributionText": "from The American Heritage® Dictionary of the English Language, 5th Edition.",
            "sourceDictionary": "ahd-5",
            "text": "A specific, characteristic period in one's lifetime.",
            "sequence": "9",
            "score": 0,
            "word": "day",
            "exampleUses": [
                {
                    "text": "In Grandmother's day, skirts were long."
                }
            ],
            "attributionUrl": "https://ahdictionary.com/",
            "wordnikUrl": "https://www.wordnik.com/words/day",
            "citations": [],
            "labels": [],
            "notes": [],
            "relatedWords": [],
            "textProns": []
        },
        {
            "id": "D5043200-10",
            "partOfSpeech": "noun",
            "attributionText": "from The American Heritage® Dictionary of the English Language, 5th Edition.",
            "sourceDictionary": "ahd-5",
            "text": "A period of opportunity or prominence.",
            "sequence": "10",
            "score": 0,
            "word": "day",
            "exampleUses": [
                {
                    "text": "Every defendant is entitled to a day in court. That child will have her day."
                }
            ],
            "attributionUrl": "https://ahdictionary.com/",
            "wordnikUrl": "https://www.wordnik.com/words/day",
            "citations": [],
            "labels": [],
            "notes": [],
            "relatedWords": [],
            "textProns": []
        }
    ]
}
